znslice/__init__.py
znslice/utils.py
znslice/znslice.py
znslice-0.1.3.dist-info/LICENSE
znslice-0.1.3.dist-info/METADATA
znslice-0.1.3.dist-info/WHEEL
znslice-0.1.3.dist-info/RECORD
