Metadata-Version: 2.1
Name: znslice
Version: 0.1.3
Summary: Cache, advanced slicing and lazy loading for __getitem__
License: Apache-2.0
Author: zincwarecode
Author-email: zincwarecode@gmail.com
Requires-Python: >=3.8,<4.0
Classifier: License :: OSI Approved :: Apache Software License
Classifier: Programming Language :: Python :: 3
Classifier: Programming Language :: Python :: 3.8
Classifier: Programming Language :: Python :: 3.9
Classifier: Programming Language :: Python :: 3.10
Classifier: Programming Language :: Python :: 3.11
Project-URL: repository, https://github.com/zincware/ZnSlice
